README.rst
setup.py
src/mezzanine_donate/__init__.py
src/mezzanine_donate/admin.py
src/mezzanine_donate/forms.py
src/mezzanine_donate/models.py
src/mezzanine_donate.egg-info/PKG-INFO
src/mezzanine_donate.egg-info/SOURCES.txt
src/mezzanine_donate.egg-info/dependency_links.txt
src/mezzanine_donate.egg-info/not-zip-safe
src/mezzanine_donate.egg-info/requires.txt
src/mezzanine_donate.egg-info/top_level.txt
src/mezzanine_donate/migrations/0001_initial.py
src/mezzanine_donate/migrations/__init__.py
src/mezzanine_donate/templates/admin
src/mezzanine_donate/templates/pages
src/mezzanine_donate/templates/admin/mezzanine_donate
src/mezzanine_donate/templates/admin/mezzanine_donate/change_form.html
src/mezzanine_donate/templates/admin/mezzanine_donate/donations.html
src/mezzanine_donate/templates/forms/horizontal.form
src/mezzanine_donate/templates/pages/donationpage.html
src/mezzanine_donate/templatetags/__init__.py
src/mezzanine_donate/templatetags/donate_tags.py