Metadata-Version: 1.1
Name: mezzanine-donate
Version: 0.1.4
Summary: Donate plugin for mezzanine using stripe for processing donations
Home-page: UNKNOWN
Author: Krzysztof Klimonda
Author-email: krzysztof@vannoppen.co
License: BSD
Platform: UNKNOWN
Classifier: Development Status :: 3 - Alpha
Classifier: Framework :: Django
Classifier: License :: OSI Approved :: BSD License
Classifier: Programming Language :: Python :: 2.6
